setup.py
idlk/__init__.py
idlk/base41.py
idlk.egg-info/PKG-INFO
idlk.egg-info/SOURCES.txt
idlk.egg-info/dependency_links.txt
idlk.egg-info/top_level.txt
idlk.egg-info/zip-safe